{
  "allquestion": [
    
    {
      "dapan": "C",
      "link": "https://i.postimg.cc/yN66JBBs/6-1-C.png",
      "helpone": ["A","D","https://i.postimg.cc/76fMpbBk/mot-6-1-C.png"],
      "helpthree": ["C", "B", "B"],
      "giaithich": "hoài sơn (củ mài) còn có tên khác: Thự dự, Sơn dược, Sơn thự, Chư thư, Ngọc duyên, Nhi thảo, Tu thúy (Ngô phổ bản thảo)"
    },
    {
      "dapan": "A",
      "link": "https://i.postimg.cc/3rdsZbZB/6-2-A.png",
      "helpone": ["C","D","https://i.postimg.cc/mDJNRRqF/mot-6-2-A.png"],
      "helpthree": ["A", "A", "A"],
      "giaithich": "động vật thân lỗ hay bọt biển, hải miên là một ngành động vật đa bào nguyên thuỷ thuộc Ngành Thân lỗ, có cấu trúc tế bào tách biệt và phần lớn là sinh sống ở biển. Cơ thể động vật thân lỗ có hình cốc gồm các tế động vật đa bào sớm nhất, phát triển từ các tập đoàn tế bào."
    },
    {
      "dapan": "B",
      "link": "https://i.postimg.cc/bwPqYDGW/6-3-B.png",
      "helpone": ["A","D","https://i.postimg.cc/j2f6Sm03/mot-6-3-B.png"],
      "helpthree": ["B", "B", "C"],
      "giaithich": "Ankara trước đây gọi là Ancyra hoặc Angora, thủ đô Thổ Nhĩ Kỳ và là thành phố lớn thứ hai của quốc gia này sau Istanbul. Là thủ đô hành chính từ thập niên 1920, Ankara đã có vai trò là trung tâm hành chính, nơi ở của các chính khách, viên chức hành chính và công chức Thổ Nhĩ Kỳ"
    }
    
  ]
}
